[{
	"ID": "english",
	"Language": "english",

	"$ItemName_AlarmBell": "alarm bell",
	"$ItemName_AlarmBellBase": "alarm bell base",
	"$ItemName_AlarmBellBell": "alarm bell bell",
	"$ItemName_Anvil": "anvil",
	"$ItemName_AppleTree": "apple tree",
	"$ItemName_Bag": "bag",
	"$ItemName_BallPeenHammer": "ballpeen hammer",
	"$ItemName_Bandage": "bandage",
	"$ItemName_Bar": "bar",
	"$ItemName_Barrel": "barrel",
	"$ItemName_Beans": "beans",
	"$ItemName_Bed": "bed",
	"$ItemName_BedFrame": "bed frame",
	"$ItemName_Beer": "beer",
	"$ItemName_Bellows": "bellows",
	"$ItemName_Berries": "berries",
	"$ItemName_Block": "block",
	"$ItemName_Bolt": "bolt of cloth",
	"$ItemName_Bone": "bone",
	"$ItemName_BoneShirt": "bone shirt",
	"$ItemName_Bread": "bread",
	"$ItemName_Bucket": "bucket",
	"$ItemName_Cabinet": "cabinet",
	"$ItemName_Chair": "chair",
	"$ItemName_Cheese": "cheese",
	"$ItemName_CheeseOmelette": "cheese omelette",
	"$ItemName_Chisel": "chisel",
	"$ItemName_Clipping": "clipping",
	"$ItemName_Coin": "coin",
	"$ItemName_Crate": "crate",
	"$ItemName_CuttingWheel": "cutting wheel",
	"$ItemName_Door": "door",
	"$ItemName_Dresser": "dresser",
	"$ItemName_Dye": "dye",
	"$ItemName_Egg": "egg",
	"$ItemName_FancyBed": "four poster bed",
	"$ItemName_FancyBedFrame": "four poster bed frame",
	"$ItemName_FellingAxeBase": "felling axe base",
	"$ItemName_FellingAxeHead": "felling axe head",
	"$ItemName_FellingAxe": "felling axe",
	"$ItemName_File": "file",
	"$ItemName_Fruit": "fruit",
	"$ItemName_Furnace": "furnace",
	"$ItemName_Gem": "gem",
	"$ItemName_GemmedRing": "gemmed ring",
	"$ItemName_GemmedNecklace": "gemmed necklace",
	"$ItemName_Grain": "grain",
	"$ItemName_Haft": "haft",
	"$ItemName_Hearth": "hearth",
	"$ItemName_Hide": "hide",
	"$ItemName_Hilt": "hilt",
	"$ItemName_Knife": "knife",
	"$ItemName_KnifeBlade": "knife blade",
	"$ItemName_KnifeHilt": "knife hilt",
	"$ItemName_LeatherStrap": "leather strap",
	"$ItemName_Leaves": "leaves",
	"$ItemName_LogFloor": "log floor",
	"$ItemName_LogWall": "log wall",
	"$ItemName_Loom": "loom",
	"$ItemName_Mattress": "mattress",
	"$ItemName_Meat": "meat",
	"$ItemName_Milk": "milk",
	"$ItemName_Mold": "mold",
	"$ItemName_Mushroom": "mushroom",
	"$ItemName_MushroomOmelette": "mushroom omelette",
	"$ItemName_Necklace": "necklace",
	"$ItemName_Needle": "needle",
	"$ItemName_OrangeTree": "orange tree",
	"$ItemName_Padding": "padding",
	"$ItemName_PetRock": "pet rock",
	"$ItemName_Pickaxe": "pickaxe",
	"$ItemName_PickaxeBase": "pickaxe base",
	"$ItemName_PickaxeHead": "pickaxe head",
	"$ItemName_Pillar": "pillar",
	"$ItemName_PineTree": "pine tree",
	"$ItemName_Plank": "plank",
	"$ItemName_PlankStairs": "plank stairs",
	"$ItemName_PuzzleBox": "puzzle box",
	"$ItemName_Radish": "fruit",
	"$ItemName_RawCloth": "raw cloth",
	"$ItemName_RawCoal": "raw coal",
	"$ItemName_RawGem": "raw gem",
	"$ItemName_RawOre": "raw ore",
	"$ItemName_RawSoil": "raw soil",
	"$ItemName_RawStone": "raw stone",
	"$ItemName_RawWood": "raw wood",
	"$ItemName_Ring": "ring",
	"$ItemName_Sandwich": "sandwich",
	"$ItemName_Sack": "sack",
	"$ItemName_Sawblade": "sawblade",
	"$ItemName_Seed": "seed",
	"$ItemName_Skull": "skull",
	"$ItemName_SkullHelmet": "skull helmet",
	"$ItemName_SoilFloor": "soil floor",
	"$ItemName_SoilStairs": "soil stairs",
	"$ItemName_SoilWall": "soil wall",
	"$ItemName_Statue": "statue",
	"$ItemName_Statuette": "statuette",
	"$ItemName_Stick": "stick",
	"$ItemName_StoneFloor": "stone floor",
	"$ItemName_StoneStairs": "stone stairs",
	"$ItemName_StoneWall": "stone wall",
	"$ItemName_Straw": "straw",
	"$ItemName_String": "string",
	"$ItemName_Sausage": "sausage",
	"$ItemName_SausageOmelette": "sausage omelette",
	"$ItemName_Table": "table",
	"$ItemName_Torch": "torch",
	"$ItemName_TrainingDummy": "training dummy",
	"$ItemName_Trough": "trough",
	"$ItemName_Vegetable": "vegetable",
	"$ItemName_Wheelbarrow": "wheelbarrow",
	"$ItemName_Wheat": "wheat",
	"$ItemName_Wine": "wine",
	"$ItemName_WoodBed": "bed",
	"$ItemName_WoodBedSheets": "bed sheets",
	"$ItemName_Workbench": "workbench",






	"$CraftName_AlarmBell": "alarm bell",
	"$CraftName_AmmoPouch": "ammo pouch",
	"$CraftName_Anvil": "anvil",
	"$CraftName_ArmorPlate": "armor plate",
	"$CraftName_ArtificialArm": "artificial arm",
	"$CraftName_ArtificialFoot": "artificial foot",
	"$CraftName_ArtificialHand": "artificial hand",
	"$CraftName_ArtificialLeg": "artificial leg",
	"$CraftName_Automaton": "automaton",
	"$CraftName_Axle": "axle",
	"$CraftName_Bag": "bag",
	"$CraftName_BallPeenHammer": "ball peen hammer",
	"$CraftName_Bandage": "bandage",
	"$CraftName_Bar": "bar",
	"$CraftName_Barrel": "barrel",
	"$CraftName_BattleAxe": "battle axe",
	"$CraftName_BattleAxeHead": "battle axe head",
	"$CraftName_Bed": "bed",
	"$CraftName_BedFrame": "bed frame",
	"$CraftName_Beer": "beer",
	"$CraftName_Bellows": "bellows",
	"$CraftName_BladeTrap": "blade trap",
	"$CraftName_Block": "block",
	"$CraftName_Blunderbuss": "blunderbuss",
	"$CraftName_BlunderbussBarrel": "blunderbuss barrel",
	"$CraftName_BlunderbussStock": "blunderbuss stock",
	"$CraftName_Bolt": "bolt",
	"$CraftName_BoneShirt": "bone shirt",
	"$CraftName_BoneStatuette": "bone statuette",
	"$CraftName_Boot": "boot",
	"$CraftName_Bread": "bread",
	"$CraftName_Breastplate": "breastplate",
	"$CraftName_BrickBlock": "brick block",
	"$CraftName_BronzeBar": "bronze bar",
	"$CraftName_Bucket": "bucket",
	"$CraftName_Cabinet": "cabinet",
	"$CraftName_Cheese": "cheese",
	"$CraftName_CheeseOmelette": "cheese omelette",
	"$CraftName_Chisel": "chisel",
	"$CraftName_ClayStatuette": "clay statuette",
	"$CraftName_Claymore": "claymore",
	"$CraftName_ClaymoreBlade": "claymore blade",
	"$CraftName_Coin": "coin",
	"$CraftName_Crate": "crate",
	"$CraftName_Crossbow": "crossbow",
	"$CraftName_CrossbowBow": "crossbow bow",
	"$CraftName_CrossbowStock": "crossbow stock",
	"$CraftName_CuttingWheel": "cutting wheel",
	"$CraftName_Cylinder": "cylinder",
	"$CraftName_Dresser": "dresser",
	"$CraftName_FancyBed": "fancy bed",
	"$CraftName_FancyBedFrame": "fancy bed frame",
	"$CraftName_FellingAxe": "felling axe",
	"$CraftName_FellingAxeHead": "felling axe head",
	"$CraftName_File": "file",
	"$CraftName_Furnace": "furnace",
	"$CraftName_FruitWine": "fruit wine",
	"$CraftName_Gauntlet": "gauntlet",
	"$CraftName_Gear": "gear",
	"$CraftName_Gearbox": "gearbox",
	"$CraftName_Gem": "gem",
	"$CraftName_GemmedNecklace": "gemmed necklace",
	"$CraftName_GemmedRing": "gemmed ring",
	"$CraftName_Greave": "greave",
	"$CraftName_Haft": "haft",
	"$CraftName_Hammer": "hammer",
	"$CraftName_HammerHead": "hammer head",
	"$CraftName_HandAxe": "hand axe",
	"$CraftName_HandAxeHead": "hand axe head",
	"$CraftName_Handcrank": "handcrank",
	"$CraftName_Hatch": "hatch",
	"$CraftName_Hearth": "hearth",
	"$CraftName_Helmet": "helmet",
	"$CraftName_Hilt": "hilt",
	"$CraftName_Knife": "knife",
	"$CraftName_KnifeBlade": "knife blade",
	"$CraftName_LeatherArmorPanel": "leather armor panel",
	"$CraftName_LeatherBoot": "leather boot",
	"$CraftName_LeatherBracer": "leather bracer",
	"$CraftName_LeatherCuirass": "leather cuirass",
	"$CraftName_LeatherGlove": "leather glove",
	"$CraftName_LeatherGreave": "leather greave",
	"$CraftName_LeatherHelm": "leather helm",
	"$CraftName_LeatherStrap": "leather strap",
	"$CraftName_Lever": "lever",
	"$CraftName_Loom": "loom",
	"$CraftName_Mattress": "mattress",
	"$CraftName_MechanicalWall": "mechanical wall",
	"$CraftName_MechanismBase": "mechanism base",
	"$CraftName_MetalCrossbowBolt": "crossbow bolt",
	"$CraftName_MetalMusketRound": "musket round",
	"$CraftName_MetalStatue": "statue",
	"$CraftName_MetalStatuette": "statuette",
	"$CraftName_Mold": "mold",
	"$CraftName_MushroomOmelette": "mushroom omelette",
	"$CraftName_Necklace": "necklace",
	"$CraftName_Needle": "needle",
	"$CraftName_Padding": "padding",
	"$CraftName_Pauldron": "pauldron",
	"$CraftName_PetRock": "pet rock",
	"$CraftName_Pickaxe": "pickaxe",
	"$CraftName_PickaxeBaseWood": "pickaxe base",
	"$CraftName_PickaxeHeadFlintStone": "pickaxe head",
	"$CraftName_PickaxeHeadStone": "pickaxe head",
	"$CraftName_PickaxeHeadWood": "pickaxe head",
	"$CraftName_Pistol": "pistol",
	"$CraftName_PistolBarrel": "pistol barral",
	"$CraftName_PistolStock": "pistol stock",
	"$CraftName_Plank": "plank",
	"$CraftName_PressurePlate": "pressure plate",
	"$CraftName_PuzzleBox": "puzzle box",
	"$CraftName_Quiver": "quiver",
	"$CraftName_RawCoal": "coal",
	"$CraftName_Ring": "ring",
	"$CraftName_Rod": "rod",
	"$CraftName_RoseGoldBar": "rosegold bar",
	"$CraftName_Sack": "sack",
	"$CraftName_Sandwich": "sandwich",
	"$CraftName_Sausage": "sausage",
	"$CraftName_SausageOmelette": "sausage omelette",
	"$CraftName_Screw": "screw",
	"$CraftName_Shield": "shield",
	"$CraftName_ShieldBacking": "shield backing",
	"$CraftName_ShieldBoss": "shield boss",
	"$CraftName_SkullHelmet": "skull helmet",
	"$CraftName_SliverBar": "bar",
	"$CraftName_Spike": "spike",
	"$CraftName_SpikeTrap": "spike trap",
	"$CraftName_Spring": "spring",
	"$CraftName_SteelBar": "steel bar",
	"$CraftName_Stick": "stick",
	"$CraftName_StoneChair": "chair",
	"$CraftName_StoneCrossbowBolt": "crossbow bolt",
	"$CraftName_StoneDoor": "door",
	"$CraftName_StoneHammer": "hammer",
	"$CraftName_StoneHandAxe": "hand axe",
	"$CraftName_StoneMusketRound": "musket round",
	"$CraftName_StonePillar": "pillar",
	"$CraftName_StoneSawblade": "saw blade",
	"$CraftName_StoneStatue": "statue",
	"$CraftName_StoneStatuette": "statuette",
	"$CraftName_StoneSword": "sword",
	"$CraftName_StoneTable": "table",
	"$CraftName_String": "string",
	"$CraftName_Sword": "sword",
	"$CraftName_SwordBlade": "sword blade",
	"$CraftName_Tea": "tea",
	"$CraftName_Tile": "tile",
	"$CraftName_Torch": "torch",
	"$CraftName_TowerShield": "tower shield",
	"$CraftName_TowerShieldBacking": "tower shield backing",
	"$CraftName_TrainingDummy": "training dummy",
	"$CraftName_TrapBase": "trap base",
	"$CraftName_Trough": "trough",
	"$CraftName_Warhammer": "warhammer",
	"$CraftName_WarhammerHead": "warhammer head",
	"$CraftName_Wheelbarrow": "wheelbarrow",
	"$CraftName_WindmillBlade": "windmill blade",
	"$CraftName_Wine": "wine",
	"$CraftName_WoodChair": "chair",
	"$CraftName_WoodDoor": "door",
	"$CraftName_WoodStatue": "statue",
	"$CraftName_WoodStatuette": "statuette",
	"$CraftName_WoodTable": "table",
	"$CraftName_WoodenShield": "shield",
	"$CraftName_Workbench": "workbench",
	"$CraftName_Wrench": "wrench",

	"$CraftName_DyedTable": "dye table",
	"$CraftName_DyedPlank": "dye plank",

	"$LAST": "Don't insert below this line!"
}]